fpflow/__init__.py
fpflow/analysis/__init__.py
fpflow/analysis/qepseudos.py
fpflow/data/create_save.txt
fpflow/data/schedulers.yaml
fpflow/data/orbitals/abacus/Ag.orb
fpflow/data/orbitals/abacus/Al.orb
fpflow/data/orbitals/abacus/Ar.orb
fpflow/data/orbitals/abacus/As.orb
fpflow/data/orbitals/abacus/Au.orb
fpflow/data/orbitals/abacus/B.orb
fpflow/data/orbitals/abacus/Ba.orb
fpflow/data/orbitals/abacus/Be.orb
fpflow/data/orbitals/abacus/Bi.orb
fpflow/data/orbitals/abacus/Br.orb
fpflow/data/orbitals/abacus/C.orb
fpflow/data/orbitals/abacus/Ca.orb
fpflow/data/orbitals/abacus/Cd.orb
fpflow/data/orbitals/abacus/Cl.orb
fpflow/data/orbitals/abacus/Co.orb
fpflow/data/orbitals/abacus/Cr.orb
fpflow/data/orbitals/abacus/Cs.orb
fpflow/data/orbitals/abacus/Cu.orb
fpflow/data/orbitals/abacus/F.orb
fpflow/data/orbitals/abacus/Fe.orb
fpflow/data/orbitals/abacus/Ga.orb
fpflow/data/orbitals/abacus/Ge.orb
fpflow/data/orbitals/abacus/H.orb
fpflow/data/orbitals/abacus/He.orb
fpflow/data/orbitals/abacus/Hf.orb
fpflow/data/orbitals/abacus/Hg.orb
fpflow/data/orbitals/abacus/I.orb
fpflow/data/orbitals/abacus/In.orb
fpflow/data/orbitals/abacus/Ir.orb
fpflow/data/orbitals/abacus/K.orb
fpflow/data/orbitals/abacus/Kr.orb
fpflow/data/orbitals/abacus/Li.orb
fpflow/data/orbitals/abacus/Mg.orb
fpflow/data/orbitals/abacus/Mn.orb
fpflow/data/orbitals/abacus/Mo.orb
fpflow/data/orbitals/abacus/N.orb
fpflow/data/orbitals/abacus/Na.orb
fpflow/data/orbitals/abacus/Nb.orb
fpflow/data/orbitals/abacus/Ne.orb
fpflow/data/orbitals/abacus/Ni.orb
fpflow/data/orbitals/abacus/O.orb
fpflow/data/orbitals/abacus/Os.orb
fpflow/data/orbitals/abacus/P.orb
fpflow/data/orbitals/abacus/Pb.orb
fpflow/data/orbitals/abacus/Pd.orb
fpflow/data/orbitals/abacus/Pt.orb
fpflow/data/orbitals/abacus/Rb.orb
fpflow/data/orbitals/abacus/Re.orb
fpflow/data/orbitals/abacus/Rh.orb
fpflow/data/orbitals/abacus/Ru.orb
fpflow/data/orbitals/abacus/S.orb
fpflow/data/orbitals/abacus/Sb.orb
fpflow/data/orbitals/abacus/Sc.orb
fpflow-1.2.0.dist-info/METADATA
fpflow-1.2.0.dist-info/WHEEL
fpflow-1.2.0.dist-info/entry_points.txt
fpflow-1.2.0.dist-info/top_level.txt
fpflow-1.2.0.dist-info/RECORD
