Metadata-Version: 2.4
Name: fpflow
Version: 1.2.0
Summary: First principles workflow
Author: Krishnaa Vadivel
Author-email: krishnaa.vadivel@yale.edu
Requires-Dist: numpy
Requires-Dist: scipy
Requires-Dist: pandas
Requires-Dist: matplotlib
Requires-Dist: ase
Requires-Dist: pyyaml
Requires-Dist: jmespath
Requires-Dist: lxml
Requires-Dist: mp_api
Requires-Dist: glom
Requires-Dist: python-benedict[all]
Requires-Dist: phonopy
Dynamic: author
Dynamic: author-email
Dynamic: description
Dynamic: requires-dist
Dynamic: summary
